<annotation><filename>1578.jpg</filename><path>/home/palm/PycharmProjects/seven/data1/2/1578.jpg</path><size><width>1080</width><height>1920</height></size><object><name>obj</name><bndbox><xmin>333</xmin><ymin>785</ymin><xmax>762</xmax><ymax>952</ymax></bndbox></object><object><name>obj</name><bndbox><xmin>689</xmin><ymin>896</ymin><xmax>917</xmax><ymax>1392</ymax></bndbox></object><object><name>obj</name><bndbox><xmin>44</xmin><ymin>1000</ymin><xmax>541</xmax><ymax>1359</ymax></bndbox></object></annotation>