<annotation><filename>1607.jpg</filename><path>/home/palm/PycharmProjects/seven/data1/2/1607.jpg</path><size><width>1080</width><height>1920</height></size><object><name>obj</name><bndbox><xmin>244</xmin><ymin>1384</ymin><xmax>618</xmax><ymax>1827</ymax></bndbox></object><object><name>obj</name><bndbox><xmin>192</xmin><ymin>662</ymin><xmax>495</xmax><ymax>1255</ymax></bndbox></object><object><name>obj</name><bndbox><xmin>572</xmin><ymin>697</ymin><xmax>810</xmax><ymax>1322</ymax></bndbox></object></annotation>