<annotation><filename>1671.jpg</filename><path>/home/palm/PycharmProjects/seven/data1/2/1671.jpg</path><size><width>1080</width><height>1920</height></size><object><name>obj</name><bndbox><xmin>113</xmin><ymin>1067</ymin><xmax>894</xmax><ymax>1421</ymax></bndbox></object><object><name>obj</name><bndbox><xmin>278</xmin><ymin>834</ymin><xmax>846</xmax><ymax>1014</ymax></bndbox></object><object><name>obj</name><bndbox><xmin>469</xmin><ymin>440</ymin><xmax>660</xmax><ymax>822</ymax></bndbox></object><object><name>obj</name><bndbox><xmin>429</xmin><ymin>1072</ymin><xmax>875</xmax><ymax>1381</ymax></bndbox></object></annotation>