<annotation><filename>1734.jpg</filename><path>/home/palm/PycharmProjects/seven/data1/2/1734.jpg</path><size><width>1080</width><height>1920</height></size><object><name>obj</name><bndbox><xmin>570</xmin><ymin>965</ymin><xmax>1000</xmax><ymax>1350</ymax></bndbox></object><object><name>obj</name><bndbox><xmin>36</xmin><ymin>852</ymin><xmax>536</xmax><ymax>1240</ymax></bndbox></object><object><name>obj</name><bndbox><xmin>753</xmin><ymin>439</ymin><xmax>960</xmax><ymax>882</ymax></bndbox></object><object><name>obj</name><bndbox><xmin>389</xmin><ymin>274</ymin><xmax>627</xmax><ymax>850</ymax></bndbox></object></annotation>