<annotation><filename>1983.jpg</filename><path>/home/palm/PycharmProjects/seven/data1/2/1983.jpg</path><size><width>1080</width><height>1920</height></size><object><name>obj</name><bndbox><xmin>502</xmin><ymin>842</ymin><xmax>851</xmax><ymax>1257</ymax></bndbox></object><object><name>obj</name><bndbox><xmin>70</xmin><ymin>845</ymin><xmax>499</xmax><ymax>1164</ymax></bndbox></object><object><name>obj</name><bndbox><xmin>577</xmin><ymin>655</ymin><xmax>776</xmax><ymax>884</ymax></bndbox></object><object><name>obj</name><bndbox><xmin>261</xmin><ymin>519</ymin><xmax>475</xmax><ymax>793</ymax></bndbox></object></annotation>