<annotation><filename>2121.jpg</filename><path>/home/palm/PycharmProjects/seven/data1/2/2121.jpg</path><size><width>1080</width><height>1920</height></size><object><name>obj</name><bndbox><xmin>487</xmin><ymin>864</ymin><xmax>884</xmax><ymax>1319</ymax></bndbox></object><object><name>obj</name><bndbox><xmin>130</xmin><ymin>803</ymin><xmax>341</xmax><ymax>1207</ymax></bndbox></object><object><name>obj</name><bndbox><xmin>489</xmin><ymin>384</ymin><xmax>651</xmax><ymax>833</ymax></bndbox></object></annotation>