<annotation><filename>311.jpg</filename><path>/home/palm/PycharmProjects/seven/data1/2/311.jpg</path><size><width>1080</width><height>1920</height></size><object><name>obj</name><bndbox><xmin>543</xmin><ymin>556</ymin><xmax>1066</xmax><ymax>1049</ymax></bndbox></object><object><name>obj</name><bndbox><xmin>399</xmin><ymin>1242</ymin><xmax>929</xmax><ymax>1718</ymax></bndbox></object><object><name>obj</name><bndbox><xmin>167</xmin><ymin>708</ymin><xmax>359</xmax><ymax>1115</ymax></bndbox></object></annotation>