<annotation><filename>392.jpg</filename><path>/home/palm/PycharmProjects/seven/data1/2/392.jpg</path><size><width>1080</width><height>1920</height></size><object><name>obj</name><bndbox><xmin>442</xmin><ymin>205</ymin><xmax>963</xmax><ymax>979</ymax></bndbox></object><object><name>obj</name><bndbox><xmin>133</xmin><ymin>1341</ymin><xmax>910</xmax><ymax>1783</ymax></bndbox></object><object><name>obj</name><bndbox><xmin>188</xmin><ymin>620</ymin><xmax>456</xmax><ymax>1097</ymax></bndbox></object></annotation>