<annotation><filename>51.jpg</filename><path>/home/palm/PycharmProjects/seven/data1/2/51.jpg</path><size><width>1080</width><height>1920</height></size><object><name>obj</name><bndbox><xmin>181</xmin><ymin>1309</ymin><xmax>920</xmax><ymax>1665</ymax></bndbox></object><object><name>obj</name><bndbox><xmin>742</xmin><ymin>869</ymin><xmax>1080</xmax><ymax>1206</ymax></bndbox></object><object><name>obj</name><bndbox><xmin>96</xmin><ymin>798</ymin><xmax>637</xmax><ymax>1014</ymax></bndbox></object></annotation>