<annotation><filename>1958.jpg</filename><path>/home/palm/PycharmProjects/seven/data1/0/1958.jpg</path><size><width>1080</width><height>1920</height></size><object><name>obj</name><bndbox><xmin>405</xmin><ymin>841</ymin><xmax>1080</xmax><ymax>1182</ymax></bndbox></object><object><name>obj</name><bndbox><xmin>90</xmin><ymin>5</ymin><xmax>748</xmax><ymax>354</ymax></bndbox></object><object><name>obj</name><bndbox><xmin>17</xmin><ymin>26</ymin><xmax>534</xmax><ymax>471</ymax></bndbox></object></annotation>