<annotation>
	<folder>0</folder>
	<filename>146.jpg</filename>
	<path>/Users/nattakarnp/Desktop/seven/images/0/146.jpg</path>
	<source>
		<database>Unknown</database>
	</source>
	<size>
		<width>1080</width>
		<height>1920</height>
		<depth>3</depth>
	</size>
	<segmented>0</segmented>
	<object>
		<name>Ferrero 62.5g</name>
		<pose>Unspecified</pose>
		<truncated>0</truncated>
		<difficult>0</difficult>
		<bndbox>
			<xmin>368</xmin>
			<ymin>465</ymin>
			<xmax>761</xmax>
			<ymax>926</ymax>
		</bndbox>
	</object>
	<object>
		<name>obj</name>
		<pose>Unspecified</pose>
		<truncated>1</truncated>
		<difficult>0</difficult>
		<bndbox>
			<xmin>1</xmin>
			<ymin>737</ymin>
			<xmax>400</xmax>
			<ymax>999</ymax>
		</bndbox>
	</object>
	<object>
		<name>Ferrero 37.5g</name>
		<pose>Unspecified</pose>
		<truncated>0</truncated>
		<difficult>0</difficult>
		<bndbox>
			<xmin>821</xmin>
			<ymin>576</ymin>
			<xmax>1024</xmax>
			<ymax>911</ymax>
		</bndbox>
	</object>
	<object>
		<name>Ferrero 100g</name>
		<pose>Unspecified</pose>
		<truncated>1</truncated>
		<difficult>0</difficult>
		<bndbox>
			<xmin>1</xmin>
			<ymin>889</ymin>
			<xmax>1080</xmax>
			<ymax>1537</ymax>
		</bndbox>
	</object>
	<object>
		<name>obj</name>
		<pose>Unspecified</pose>
		<truncated>0</truncated>
		<difficult>0</difficult>
		<bndbox>
			<xmin>34</xmin>
			<ymin>556</ymin>
			<xmax>309</xmax>
			<ymax>821</ymax>
		</bndbox>
	</object>
</annotation>
