<annotation>
	<folder>0</folder>
	<filename>455.jpg</filename>
	<path>/home/palm/PycharmProjects/seven/data1/0/455.jpg</path>
	<source>
		<database>Unknown</database>
	</source>
	<size>
		<width>1080</width>
		<height>1920</height>
		<depth>3</depth>
	</size>
	<segmented>0</segmented>
	<object>
		<name>obj</name>
		<pose>Unspecified</pose>
		<truncated>0</truncated>
		<difficult>0</difficult>
		<bndbox>
			<xmin>9</xmin>
			<ymin>841</ymin>
			<xmax>422</xmax>
			<ymax>1385</ymax>
		</bndbox>
	</object>
	<object>
		<name>obj</name>
		<pose>Unspecified</pose>
		<truncated>0</truncated>
		<difficult>0</difficult>
		<bndbox>
			<xmin>139</xmin>
			<ymin>407</ymin>
			<xmax>382</xmax>
			<ymax>795</ymax>
		</bndbox>
	</object>
	<object>
		<name>obj</name>
		<pose>Unspecified</pose>
		<truncated>0</truncated>
		<difficult>0</difficult>
		<bndbox>
			<xmin>740</xmin>
			<ymin>703</ymin>
			<xmax>1066</xmax>
			<ymax>1053</ymax>
		</bndbox>
	</object>
	<object>
		<name>obj</name>
		<pose>Unspecified</pose>
		<truncated>0</truncated>
		<difficult>0</difficult>
		<bndbox>
			<xmin>388</xmin>
			<ymin>247</ymin>
			<xmax>655</xmax>
			<ymax>543</ymax>
		</bndbox>
	</object>
	<object>
		<name>obj</name>
		<pose>Unspecified</pose>
		<truncated>1</truncated>
		<difficult>0</difficult>
		<bndbox>
			<xmin>653</xmin>
			<ymin>463</ymin>
			<xmax>1080</xmax>
			<ymax>629</ymax>
		</bndbox>
	</object>
</annotation>
