<annotation><filename>1101.jpg</filename><path>/home/palm/PycharmProjects/seven/data1/1/1101.jpg</path><size><width>1080</width><height>1920</height></size><object><name>obj</name><bndbox><xmin>427</xmin><ymin>762</ymin><xmax>1040</xmax><ymax>1414</ymax></bndbox></object><object><name>obj</name><bndbox><xmin>0</xmin><ymin>1046</ymin><xmax>374</xmax><ymax>1538</ymax></bndbox></object><object><name>obj</name><bndbox><xmin>627</xmin><ymin>0</ymin><xmax>1047</xmax><ymax>502</ymax></bndbox></object></annotation>