<annotation><filename>161.jpg</filename><path>/home/palm/PycharmProjects/seven/data1/1/161.jpg</path><size><width>1080</width><height>1920</height></size><object><name>obj</name><bndbox><xmin>81</xmin><ymin>1066</ymin><xmax>544</xmax><ymax>1551</ymax></bndbox></object><object><name>obj</name><bndbox><xmin>332</xmin><ymin>655</ymin><xmax>803</xmax><ymax>1146</ymax></bndbox></object><object><name>obj</name><bndbox><xmin>158</xmin><ymin>536</ymin><xmax>732</xmax><ymax>1096</ymax></bndbox></object><object><name>obj</name><bndbox><xmin>108</xmin><ymin>481</ymin><xmax>432</xmax><ymax>936</ymax></bndbox></object><object><name>obj</name><bndbox><xmin>16</xmin><ymin>0</ymin><xmax>254</xmax><ymax>506</ymax></bndbox></object></annotation>