<annotation><filename>280.jpg</filename><path>/home/palm/PycharmProjects/seven/data1/1/280.jpg</path><size><width>1080</width><height>1920</height></size><object><name>obj</name><bndbox><xmin>214</xmin><ymin>651</ymin><xmax>636</xmax><ymax>1364</ymax></bndbox></object><object><name>obj</name><bndbox><xmin>457</xmin><ymin>0</ymin><xmax>1080</xmax><ymax>833</ymax></bndbox></object><object><name>obj</name><bndbox><xmin>562</xmin><ymin>889</ymin><xmax>1080</xmax><ymax>1809</ymax></bndbox></object></annotation>