<annotation><filename>402.jpg</filename><path>/home/palm/PycharmProjects/seven/data1/1/402.jpg</path><size><width>1080</width><height>1920</height></size><object><name>obj</name><bndbox><xmin>192</xmin><ymin>921</ymin><xmax>428</xmax><ymax>1305</ymax></bndbox></object><object><name>obj</name><bndbox><xmin>484</xmin><ymin>1195</ymin><xmax>759</xmax><ymax>1588</ymax></bndbox></object><object><name>obj</name><bndbox><xmin>631</xmin><ymin>22</ymin><xmax>983</xmax><ymax>457</ymax></bndbox></object></annotation>