<annotation><filename>489.jpg</filename><path>/home/palm/PycharmProjects/seven/data1/1/489.jpg</path><size><width>1080</width><height>1920</height></size><object><name>obj</name><bndbox><xmin>129</xmin><ymin>1343</ymin><xmax>741</xmax><ymax>1753</ymax></bndbox></object><object><name>obj</name><bndbox><xmin>0</xmin><ymin>1077</ymin><xmax>582</xmax><ymax>1330</ymax></bndbox></object><object><name>obj</name><bndbox><xmin>448</xmin><ymin>804</ymin><xmax>1023</xmax><ymax>1038</ymax></bndbox></object><object><name>obj</name><bndbox><xmin>628</xmin><ymin>32</ymin><xmax>977</xmax><ymax>466</ymax></bndbox></object><object><name>obj</name><bndbox><xmin>193</xmin><ymin>1053</ymin><xmax>602</xmax><ymax>1273</ymax></bndbox></object></annotation>