<annotation><filename>495.jpg</filename><path>/home/palm/PycharmProjects/seven/data1/1/495.jpg</path><size><width>1080</width><height>1920</height></size><object><name>obj</name><bndbox><xmin>183</xmin><ymin>1542</ymin><xmax>868</xmax><ymax>1833</ymax></bndbox></object><object><name>obj</name><bndbox><xmin>148</xmin><ymin>1221</ymin><xmax>784</xmax><ymax>1439</ymax></bndbox></object><object><name>obj</name><bndbox><xmin>143</xmin><ymin>749</ymin><xmax>727</xmax><ymax>1063</ymax></bndbox></object><object><name>obj</name><bndbox><xmin>635</xmin><ymin>20</ymin><xmax>981</xmax><ymax>460</ymax></bndbox></object><object><name>obj</name><bndbox><xmin>467</xmin><ymin>1538</ymin><xmax>904</xmax><ymax>1790</ymax></bndbox></object><object><name>obj</name><bndbox><xmin>433</xmin><ymin>1210</ymin><xmax>812</xmax><ymax>1418</ymax></bndbox></object></annotation>