<annotation><filename>563.jpg</filename><path>/home/palm/PycharmProjects/seven/data1/1/563.jpg</path><size><width>1080</width><height>1920</height></size><object><name>obj</name><bndbox><xmin>406</xmin><ymin>267</ymin><xmax>826</xmax><ymax>1268</ymax></bndbox></object><object><name>obj</name><bndbox><xmin>19</xmin><ymin>877</ymin><xmax>315</xmax><ymax>1470</ymax></bndbox></object><object><name>obj</name><bndbox><xmin>389</xmin><ymin>1510</ymin><xmax>949</xmax><ymax>1920</ymax></bndbox></object><object><name>obj</name><bndbox><xmin>339</xmin><ymin>631</ymin><xmax>748</xmax><ymax>1289</ymax></bndbox></object></annotation>