<annotation><filename>773.jpg</filename><path>/home/palm/PycharmProjects/seven/data1/1/773.jpg</path><size><width>1080</width><height>1920</height></size><object><name>obj</name><bndbox><xmin>182</xmin><ymin>581</ymin><xmax>690</xmax><ymax>1195</ymax></bndbox></object><object><name>obj</name><bndbox><xmin>528</xmin><ymin>939</ymin><xmax>1080</xmax><ymax>1874</ymax></bndbox></object><object><name>obj</name><bndbox><xmin>121</xmin><ymin>1436</ymin><xmax>513</xmax><ymax>1920</ymax></bndbox></object><object><name>obj</name><bndbox><xmin>11</xmin><ymin>920</ymin><xmax>185</xmax><ymax>1405</ymax></bndbox></object></annotation>