<annotation><filename>813.jpg</filename><path>/home/palm/PycharmProjects/seven/data1/1/813.jpg</path><size><width>1080</width><height>1920</height></size><object><name>obj</name><bndbox><xmin>332</xmin><ymin>1244</ymin><xmax>806</xmax><ymax>1757</ymax></bndbox></object><object><name>obj</name><bndbox><xmin>323</xmin><ymin>757</ymin><xmax>808</xmax><ymax>1082</ymax></bndbox></object><object><name>obj</name><bndbox><xmin>22</xmin><ymin>877</ymin><xmax>284</xmax><ymax>1298</ymax></bndbox></object><object><name>obj</name><bndbox><xmin>588</xmin><ymin>2</ymin><xmax>1000</xmax><ymax>462</ymax></bndbox></object><object><name>obj</name><bndbox><xmin>58</xmin><ymin>1230</ymin><xmax>320</xmax><ymax>1568</ymax></bndbox></object></annotation>