<annotation><filename>825.jpg</filename><path>/home/palm/PycharmProjects/seven/data1/1/825.jpg</path><size><width>1080</width><height>1920</height></size><object><name>obj</name><bndbox><xmin>334</xmin><ymin>711</ymin><xmax>802</xmax><ymax>1094</ymax></bndbox></object><object><name>obj</name><bndbox><xmin>485</xmin><ymin>1111</ymin><xmax>1042</xmax><ymax>1679</ymax></bndbox></object><object><name>obj</name><bndbox><xmin>17</xmin><ymin>1002</ymin><xmax>330</xmax><ymax>1380</ymax></bndbox></object><object><name>obj</name><bndbox><xmin>91</xmin><ymin>1394</ymin><xmax>387</xmax><ymax>1733</ymax></bndbox></object><object><name>obj</name><bndbox><xmin>645</xmin><ymin>2</ymin><xmax>979</xmax><ymax>494</ymax></bndbox></object></annotation>