<annotation>
	<folder>1</folder>
	<filename>8.jpg</filename>
	<path>/home/palm/PycharmProjects/seven/data1/1/8.jpg</path>
	<source>
		<database>Unknown</database>
	</source>
	<size>
		<width>1080</width>
		<height>1920</height>
		<depth>3</depth>
	</size>
	<segmented>0</segmented>
	<object>
		<name>obj</name>
		<pose>Unspecified</pose>
		<truncated>0</truncated>
		<difficult>0</difficult>
		<bndbox>
			<xmin>241</xmin>
			<ymin>1352</ymin>
			<xmax>700</xmax>
			<ymax>1805</ymax>
		</bndbox>
	</object>
	<object>
		<name>obj</name>
		<pose>Unspecified</pose>
		<truncated>1</truncated>
		<difficult>0</difficult>
		<bndbox>
			<xmin>1</xmin>
			<ymin>1190</ymin>
			<xmax>434</xmax>
			<ymax>1523</ymax>
		</bndbox>
	</object>
	<object>
		<name>obj</name>
		<pose>Unspecified</pose>
		<truncated>1</truncated>
		<difficult>0</difficult>
		<bndbox>
			<xmin>774</xmin>
			<ymin>1247</ymin>
			<xmax>1080</xmax>
			<ymax>1622</ymax>
		</bndbox>
	</object>
	<object>
		<name>obj</name>
		<pose>Unspecified</pose>
		<truncated>0</truncated>
		<difficult>0</difficult>
		<bndbox>
			<xmin>496</xmin>
			<ymin>1097</ymin>
			<xmax>798</xmax>
			<ymax>1314</ymax>
		</bndbox>
	</object>
	<object>
		<name>obj</name>
		<pose>Unspecified</pose>
		<truncated>0</truncated>
		<difficult>0</difficult>
		<bndbox>
			<xmin>276</xmin>
			<ymin>977</ymin>
			<xmax>548</xmax>
			<ymax>1143</ymax>
		</bndbox>
	</object>
	<object>
		<name>obj</name>
		<pose>Unspecified</pose>
		<truncated>0</truncated>
		<difficult>0</difficult>
		<bndbox>
			<xmin>142</xmin>
			<ymin>933</ymin>
			<xmax>280</xmax>
			<ymax>1187</ymax>
		</bndbox>
	</object>
	<object>
		<name>obj</name>
		<pose>Unspecified</pose>
		<truncated>0</truncated>
		<difficult>0</difficult>
		<bndbox>
			<xmin>137</xmin>
			<ymin>677</ymin>
			<xmax>462</xmax>
			<ymax>925</ymax>
		</bndbox>
	</object>
	<object>
		<name>obj</name>
		<pose>Unspecified</pose>
		<truncated>0</truncated>
		<difficult>0</difficult>
		<bndbox>
			<xmin>463</xmin>
			<ymin>941</ymin>
			<xmax>770</xmax>
			<ymax>1131</ymax>
		</bndbox>
	</object>
</annotation>
