<annotation>
	<folder>1</folder>
	<filename>92.jpg</filename>
	<path>/home/palm/PycharmProjects/seven/data1/1/92.jpg</path>
	<source>
		<database>Unknown</database>
	</source>
	<size>
		<width>1080</width>
		<height>1920</height>
		<depth>3</depth>
	</size>
	<segmented>0</segmented>
	<object>
		<name>obj</name>
		<pose>Unspecified</pose>
		<truncated>0</truncated>
		<difficult>0</difficult>
		<bndbox>
			<xmin>476</xmin>
			<ymin>488</ymin>
			<xmax>940</xmax>
			<ymax>962</ymax>
		</bndbox>
	</object>
	<object>
		<name>obj</name>
		<pose>Unspecified</pose>
		<truncated>0</truncated>
		<difficult>0</difficult>
		<bndbox>
			<xmin>206</xmin>
			<ymin>527</ymin>
			<xmax>476</xmax>
			<ymax>770</ymax>
		</bndbox>
	</object>
	<object>
		<name>obj</name>
		<pose>Unspecified</pose>
		<truncated>0</truncated>
		<difficult>0</difficult>
		<bndbox>
			<xmin>152</xmin>
			<ymin>826</ymin>
			<xmax>424</xmax>
			<ymax>1029</ymax>
		</bndbox>
	</object>
	<object>
		<name>obj</name>
		<pose>Unspecified</pose>
		<truncated>0</truncated>
		<difficult>0</difficult>
		<bndbox>
			<xmin>439</xmin>
			<ymin>802</ymin>
			<xmax>810</xmax>
			<ymax>1226</ymax>
		</bndbox>
	</object>
	<object>
		<name>obj</name>
		<pose>Unspecified</pose>
		<truncated>0</truncated>
		<difficult>0</difficult>
		<bndbox>
			<xmin>89</xmin>
			<ymin>967</ymin>
			<xmax>324</xmax>
			<ymax>1149</ymax>
		</bndbox>
	</object>
	<object>
		<name>obj</name>
		<pose>Unspecified</pose>
		<truncated>0</truncated>
		<difficult>0</difficult>
		<bndbox>
			<xmin>157</xmin>
			<ymin>1361</ymin>
			<xmax>351</xmax>
			<ymax>1628</ymax>
		</bndbox>
	</object>
	<object>
		<name>obj</name>
		<pose>Unspecified</pose>
		<truncated>0</truncated>
		<difficult>0</difficult>
		<bndbox>
			<xmin>21</xmin>
			<ymin>1140</ymin>
			<xmax>222</xmax>
			<ymax>1399</ymax>
		</bndbox>
	</object>
	<object>
		<name>obj</name>
		<pose>Unspecified</pose>
		<truncated>0</truncated>
		<difficult>0</difficult>
		<bndbox>
			<xmin>4</xmin>
			<ymin>677</ymin>
			<xmax>88</xmax>
			<ymax>1027</ymax>
		</bndbox>
	</object>
	<object>
		<name>obj</name>
		<pose>Unspecified</pose>
		<truncated>0</truncated>
		<difficult>0</difficult>
		<bndbox>
			<xmin>90</xmin>
			<ymin>1265</ymin>
			<xmax>508</xmax>
			<ymax>1413</ymax>
		</bndbox>
	</object>
</annotation>
